leadtimer/__init__.py
leadtimer/time_mean/__init__.py
leadtimer/time_mean/time_mean.py
leadtimer/timescale/__init__.py
leadtimer/timescale/timescale.py
leadtimer-0.0.2.dist-info/METADATA
leadtimer-0.0.2.dist-info/WHEEL
leadtimer-0.0.2.dist-info/top_level.txt
leadtimer-0.0.2.dist-info/RECORD
