Metadata-Version: 2.4
Name: leadtimer
Version: 0.0.2
Summary: Простая и удобная в использовании библиотека для рассчета времни выполнения кода на языке Python
Author-email: 1132246169 <1132246169@pfur.ru>
Maintainer-email: 1132246169 <1132246169@pfur.ru>
Classifier: Programming Language :: Python :: 3
Classifier: Operating System :: OS Independent
Requires-Python: >=3.14
Provides-Extra: test
Requires-Dist: pytest; extra == "test"
